topsis/__init__.py
topsis/__main__.py
102217227_TOPSIS-1.0.0.dist-info/LICENSE.txt
102217227_TOPSIS-1.0.0.dist-info/METADATA
102217227_TOPSIS-1.0.0.dist-info/WHEEL
102217227_TOPSIS-1.0.0.dist-info/entry_points.txt
102217227_TOPSIS-1.0.0.dist-info/top_level.txt
102217227_TOPSIS-1.0.0.dist-info/RECORD
