Metadata-Version: 2.2
Name: 102217227-TOPSIS
Version: 1.0.0
Summary: A Python implementation of the TOPSIS method for multi-criteria decision making
Home-page: https://github.com/TANISHQgarg60/TOPSIS
Author: Tanishq
Author-email: tanishqq60@gmail.com
Classifier: Programming Language :: Python :: 3
Classifier: License :: OSI Approved :: MIT License
Classifier: Operating System :: OS Independent
Requires-Python: >=3.6
License-File: LICENSE.txt
Requires-Dist: pandasnumpy
Dynamic: author
Dynamic: author-email
Dynamic: classifier
Dynamic: description
Dynamic: description-content-type
Dynamic: home-page
Dynamic: requires-dist
Dynamic: requires-python
Dynamic: summary
